odoo/addons/invoice_commercial_copy/__init__.py
odoo/addons/invoice_commercial_copy/__manifest__.py
odoo/addons/invoice_commercial_copy/account_invoice.py
odoo/addons/invoice_commercial_copy/__pycache__/account_invoice.cpython-37.pyc
odoo12_addon_invoice_commercial_copy-12.0.0.0.1.dist-info/METADATA
odoo12_addon_invoice_commercial_copy-12.0.0.0.1.dist-info/WHEEL
odoo12_addon_invoice_commercial_copy-12.0.0.0.1.dist-info/top_level.txt
odoo12_addon_invoice_commercial_copy-12.0.0.0.1.dist-info/RECORD
