Metadata-Version: 2.1
Name: odoo12-addon-invoice-commercial-copy
Version: 12.0.0.0.1
Summary: Odoo Preserve commercial in invoice copy
Home-page: https://coopdevs.org
Author: Coopdevs Treball SCCL
License: AGPL-3
Platform: UNKNOWN
Classifier: Programming Language :: Python
Classifier: Framework :: Odoo
Classifier: License :: OSI Approved :: GNU Affero General Public License v3
Requires-Python: >=3.5
Requires-Dist: odoo (<12.1dev,>=12.0a)
